deepts_forecasting/__init__.py
deepts_forecasting/datasets/__init__.py
deepts_forecasting/datasets/data/AirPassengers.csv
deepts_forecasting/datasets/data/Store_Demand/test.csv
deepts_forecasting/datasets/data/Store_Demand/train.csv
deepts_forecasting/datasets/data/energy_dataset.csv
deepts_forecasting/datasets/data/monthly-sunspots.csv
deepts_forecasting/datasets/data/temps.csv
deepts_forecasting/datasets/get_data.py
deepts_forecasting/logging/__init__.py
deepts_forecasting/logging/logging.py
deepts_forecasting/metrics/__init__.py
deepts_forecasting/metrics/metrics.py
deepts_forecasting/models/__init__.py
deepts_forecasting/models/autoformer/__init__.py
deepts_forecasting/models/autoformer/attention.py
deepts_forecasting/models/autoformer/autoformer.py
deepts_forecasting/models/autoformer/mask.py
deepts_forecasting/models/autoformer/sub_module.py
deepts_forecasting/models/base_model.py
deepts_forecasting/models/darnn/__init__.py
deepts_forecasting/models/deepar/__init__.py
deepts_forecasting/models/informer/__init__.py
deepts_forecasting/models/informer/attention.py
deepts_forecasting/models/informer/embedding.py
deepts_forecasting/models/informer/informer.py
deepts_forecasting/models/informer/mask.py
deepts_forecasting/models/informer/sub_module.py
deepts_forecasting/models/lstnet/__init__.py
deepts_forecasting/models/lstnet/sub_modules.py
deepts_forecasting/models/modules/__init__.py
deepts_forecasting/models/modules/embedding.py
deepts_forecasting/models/modules/time2vec.py
deepts_forecasting/models/modules/timedistributed.py
deepts_forecasting/models/mqrnn/__init__.py
deepts_forecasting/models/nbeats/__init__.py
deepts_forecasting/models/nbeats/nbeats.py
deepts_forecasting/models/nbeats/sub_modules.py
deepts_forecasting/models/seq2seq/__init__.py
deepts_forecasting/models/tcn/__init__.py
deepts_forecasting/models/tcn/tcn.py
deepts_forecasting/models/tft/__init__.py
deepts_forecasting/models/tft/sub_module.py
deepts_forecasting/models/tft/tft.py
deepts_forecasting-0.1.2.dist-info/LICENSE
deepts_forecasting-0.1.2.dist-info/WHEEL
deepts_forecasting-0.1.2.dist-info/METADATA
deepts_forecasting-0.1.2.dist-info/RECORD
